vermon/__about__.py
vermon/__init__.py
vermon/core.py
vermon/exceptions.py
vermon-0.1.0.dist-info/LICENSE
vermon-0.1.0.dist-info/METADATA
vermon-0.1.0.dist-info/WHEEL
vermon-0.1.0.dist-info/top_level.txt
vermon-0.1.0.dist-info/RECORD
