Metadata-Version: 2.1
Name: vermon
Version: 0.1.0
Summary: Check for a newer version of your package and notify the user about it
Home-page: https://github.com/matheusfelipeog/vermon
Author: Matheus Felipe
Author-email: matheusfelipeog@protonmail.com
License: MIT License
Project-URL: Bug Tracker, https://github.com/matheusfelipeog/vermon/issues
Project-URL: Documentation, https://github.com/matheusfelipeog/vermon
Project-URL: Source Code, https://github.com/matheusfelipeog/vermon
Keywords: vermon,version-monitoring,version-check,vermon-package,version-newer,package-monitoring,notify
Platform: UNKNOWN
Classifier: Development Status :: 4 - Beta
Classifier: Intended Audience :: Developers
Classifier: Intended Audience :: Information Technology
Classifier: License :: OSI Approved :: MIT License
Classifier: Natural Language :: English
Classifier: Operating System :: OS Independent
Classifier: Programming Language :: Python
Classifier: Programming Language :: Python :: 3.6
Classifier: Programming Language :: Python :: 3.7
Classifier: Programming Language :: Python :: 3.8
Classifier: Programming Language :: Python :: 3.9
Classifier: Programming Language :: Python :: Implementation :: CPython
Classifier: Topic :: Software Development :: Libraries
Classifier: Topic :: Software Development :: Libraries :: Python Modules
Requires-Python: >=3.6
Requires-Dist: requests
